pathling/__init__.py
pathling/_version.py
pathling/bulk.py
pathling/coding.py
pathling/context.py
pathling/core.py
pathling/datasink.py
pathling/datasource.py
pathling/fhir.py
pathling/functions.py
pathling/spark.py
pathling/udfs.py
pathling-9.2.0.data/data/share/pathling/examples/bulk.py
pathling-9.2.0.data/data/share/pathling/examples/designation.py
pathling-9.2.0.data/data/share/pathling/examples/display.py
pathling-9.2.0.data/data/share/pathling/examples/encode_bundles.py
pathling-9.2.0.data/data/share/pathling/examples/encode_resources.py
pathling-9.2.0.data/data/share/pathling/examples/fhir_view.py
pathling-9.2.0.data/data/share/pathling/examples/member_of.py
pathling-9.2.0.data/data/share/pathling/examples/property_of.py
pathling-9.2.0.data/data/share/pathling/examples/subsumes.py
pathling-9.2.0.data/data/share/pathling/examples/translate.py
pathling-9.2.0.data/data/share/pathling/examples/data/bundles/Bennett146_Swaniawski813_704c9750-f6e6-473b-ee83-fbd48e07fe3f.json
pathling-9.2.0.data/data/share/pathling/examples/data/bundles/Dino214_Parisian75_40d82b80-b682-cd8b-da6d-396809878641.json
pathling-9.2.0.data/data/share/pathling/examples/data/csv/conditions.csv
pathling-9.2.0.data/data/share/pathling/examples/data/resources/Condition.ndjson
pathling-9.2.0.data/data/share/pathling/examples/data/resources/Patient.ndjson
pathling-9.2.0.dist-info/METADATA
pathling-9.2.0.dist-info/WHEEL
pathling-9.2.0.dist-info/licenses/LICENSE
pathling-9.2.0.dist-info/RECORD
