Metadata-Version: 2.4
Name: pathling
Version: 9.2.0
Summary: Python API for Pathling
Project-URL: Homepage, https://github.com/aehrc/pathling
Author-email: "Australian e-Health Research Centre, CSIRO" <pathling@csiro.au>
License: Apache License, version 2.0
License-File: LICENSE
Keywords: analytics,fhir,pathling,spark,standards,terminology
Classifier: Development Status :: 3 - Alpha
Classifier: License :: OSI Approved :: Apache Software License
Classifier: Programming Language :: Python :: 3.9
Classifier: Programming Language :: Python :: 3.10
Classifier: Programming Language :: Python :: 3.11
Requires-Python: >=3.9
Requires-Dist: deprecated>=1.2.13
Requires-Dist: pyspark<4.1.0,>=4.0.0
